mastodon/Mastodon.py
mastodon/__init__.py
mastodon/_url_regex.py
mastodon/accounts.py
mastodon/admin.py
mastodon/authentication.py
mastodon/compat.py
mastodon/conversations.py
mastodon/defaults.py
mastodon/endorsements.py
mastodon/errors.py
mastodon/favourites.py
mastodon/filters.py
mastodon/hashtags.py
mastodon/instance.py
mastodon/internals.py
mastodon/lists.py
mastodon/media.py
mastodon/notifications.py
mastodon/polls.py
mastodon/preferences.py
mastodon/push.py
mastodon/py.typed
mastodon/relationships.py
mastodon/reports.py
mastodon/return_types.py
mastodon/search.py
mastodon/statuses.py
mastodon/streaming.py
mastodon/streaming_endpoints.py
mastodon/suggestions.py
mastodon/timeline.py
mastodon/trends.py
mastodon/types_base.py
mastodon/utility.py
mastodon/versions.py
mastodon_py-2.1.3.dist-info/licenses/LICENSE
mastodon_py-2.1.3.dist-info/METADATA
mastodon_py-2.1.3.dist-info/WHEEL
mastodon_py-2.1.3.dist-info/top_level.txt
mastodon_py-2.1.3.dist-info/RECORD
