Metadata-Version: 2.4
Name: Mastodon.py
Version: 2.1.3
Summary: Python wrapper for the Mastodon API
Author-email: Lorenz Diener <lorenzd+mastodonpypypi@gmail.com>
License: MIT
Project-URL: Repository, https://github.com/halcy/Mastodon.py
Project-URL: Documentation, https://mastodonpy.readthedocs.io/
Keywords: mastodon,api,microblogging
Classifier: Development Status :: 5 - Production/Stable
Classifier: Intended Audience :: Developers
Classifier: Topic :: Communications
Classifier: License :: OSI Approved :: MIT License
Classifier: Programming Language :: Python :: 2
Classifier: Programming Language :: Python :: 3
License-File: LICENSE
Requires-Dist: requests>=2.4.2
Requires-Dist: python-dateutil
Requires-Dist: python-magic-bin; platform_system == "Windows"
Requires-Dist: python-magic; platform_system != "Windows"
Requires-Dist: decorator>=4.0.0
Requires-Dist: blurhash>=1.1.4
Provides-Extra: webpush
Requires-Dist: http_ece>=1.0.5; extra == "webpush"
Requires-Dist: cryptography>=1.6.0; extra == "webpush"
Provides-Extra: blurhash
Requires-Dist: blurhash>=1.1.4; extra == "blurhash"
Provides-Extra: grapheme
Requires-Dist: grapheme>=0.6.0; extra == "grapheme"
Provides-Extra: test
Requires-Dist: pytest; extra == "test"
Requires-Dist: pytest-cov; extra == "test"
Requires-Dist: vcrpy; extra == "test"
Requires-Dist: pytest-recording; extra == "test"
Requires-Dist: pytest-mock; extra == "test"
Requires-Dist: requests-mock; extra == "test"
Requires-Dist: pytz; extra == "test"
Requires-Dist: pytest-retry; extra == "test"
Provides-Extra: test-old
Requires-Dist: pytest; extra == "test-old"
Requires-Dist: pytest-cov; extra == "test-old"
Requires-Dist: vcrpy; extra == "test-old"
Requires-Dist: pytest-recording; extra == "test-old"
Requires-Dist: pytest-mock; extra == "test-old"
Requires-Dist: requests-mock; extra == "test-old"
Requires-Dist: pytz; extra == "test-old"
Provides-Extra: docs
Requires-Dist: sphinx-rtd-theme; extra == "docs"
Dynamic: license-file
